pyd2v/__init__.py
pyd2v/__main__.py
pyd2v/d2v.py
pyd2v-1.4.0.dist-info/LICENSE
pyd2v-1.4.0.dist-info/METADATA
pyd2v-1.4.0.dist-info/WHEEL
pyd2v-1.4.0.dist-info/entry_points.txt
pyd2v-1.4.0.dist-info/RECORD
