Metadata-Version: 2.1
Name: pyd2v
Version: 1.4.0
Summary: A Python Parser for DGMPGDec's D2V Project Files.
Home-page: https://github.com/rlaphoenix/pyd2v
License: MIT
Keywords: python,d2v,dgindex,dgmpgdec,mpeg
Author: PHOENiX
Author-email: rlaphoenix@pm.me
Maintainer: PHOENiX
Maintainer-email: rlaphoenix@pm.me
Requires-Python: >=3.7,<4.0
Classifier: Development Status :: 5 - Production/Stable
Classifier: Environment :: Console
Classifier: Intended Audience :: Developers
Classifier: License :: OSI Approved :: MIT License
Classifier: Natural Language :: English
Classifier: Operating System :: OS Independent
Classifier: Programming Language :: Python :: 3
Classifier: Programming Language :: Python :: 3.7
Classifier: Programming Language :: Python :: 3.8
Classifier: Programming Language :: Python :: 3.9
Classifier: Programming Language :: Python :: 3.10
Classifier: Programming Language :: Python :: 3.11
Classifier: Topic :: Multimedia :: Video
Requires-Dist: click (>=8.1.7,<9.0.0)
Requires-Dist: jsonpickle (>=3.0.2,<4.0.0)
Project-URL: Repository, https://github.com/rlaphoenix/pyd2v
